sample-files/__init__.py
sample-files/no_delete.py
sample-files/pycache.py
sample-files/migrations/0001_initial.py
sample-files/migrations/0002_other.py
sample-files/migrations/__init__.py
tests/__init__.py
tests/resetmigrations_clean_test.py
tests/sample-files/__init__.py
tests/sample-files/no_delete.py
tests/sample-files/pycache.py
tests/sample-files/migrations/__init__.py
resetmigrations-0.0.5.dist-info/METADATA
resetmigrations-0.0.5.dist-info/WHEEL
resetmigrations-0.0.5.dist-info/entry_points.txt
resetmigrations-0.0.5.dist-info/top_level.txt
resetmigrations-0.0.5.dist-info/RECORD
