Metadata-Version: 2.1
Name: resetmigrations
Version: 0.0.5
Summary: UNKNOWN
Home-page: UNKNOWN
Author: Juan Cruz Maciel Henning
License: UNKNOWN
Platform: UNKNOWN
Requires-Dist: click
Requires-Dist: rich
